CHANGELOG.rst
CONTRIBUTORS.txt
dj_blacksmith-5.0.1.dist-info/METADATA
dj_blacksmith-5.0.1.dist-info/WHEEL
dj_blacksmith-5.0.1.dist-info/entry_points.txt
dj_blacksmith-5.0.1.dist-info/licenses/LICENSE
dj_blacksmith/__init__.py
dj_blacksmith/_settings.py
dj_blacksmith/apps.py
dj_blacksmith/client/__init__.py
dj_blacksmith/client/_async/__init__.py
dj_blacksmith/client/_async/client.py
dj_blacksmith/client/_async/middleware.py
dj_blacksmith/client/_async/middleware_factory.py
dj_blacksmith/client/_sync/__init__.py
dj_blacksmith/client/_sync/client.py
dj_blacksmith/client/_sync/middleware.py
dj_blacksmith/client/_sync/middleware_factory.py
dj_blacksmith/py.typed
dj_blacksmith-5.0.1.dist-info/RECORD
