Metadata-Version: 2.1
Name: dj-blacksmith
Version: 5.0.1
Summary: Django Bindings for Blacksmith
Author-Email: Guillaume Gauvrit <guillaume@gauvr.it>
License: MIT
Classifier: Development Status :: 5 - Production/Stable
Classifier: Framework :: Django
Classifier: Intended Audience :: Developers
Classifier: License :: OSI Approved :: MIT License
Classifier: Topic :: Software Development :: Libraries :: Python Modules
Classifier: Topic :: Internet :: WWW/HTTP
Project-URL: Homepage, https://github.com/mardiros/dj-blacksmith
Project-URL: Documentation, https://github.com/mardiros/dj-blacksmith/blob/main/README.rst
Project-URL: Repository, https://github.com/mardiros/dj-blacksmith.git
Project-URL: Issues, https://github.com/mardiros/dj-blacksmith/issues
Project-URL: Changelog, https://github.com/mardiros/dj-blacksmith/blob/main/CHANGELOG.rst
Requires-Python: >=3.10
Requires-Dist: django<=7,>=4.0.0
Requires-Dist: blacksmith[prometheus]<6,>=5.0.0
Requires-Dist: redis<5,>=4.2.0
Provides-Extra: docs
Requires-Dist: sphinx>=7.0.0; extra == "docs"
Requires-Dist: sphinx-autodoc-typehints<2,>=1.12.0; extra == "docs"
Requires-Dist: furo>=2024.8.6; extra == "docs"
